pytypegen/__init__.py
pytypegen/__init__.pyi
pytypegen/core.py
pytypegen/core.pyi
pytypegen/debugger.py
pytypegen/debugger.pyi
pytypegen/exceptions.py
pytypegen/exceptions.pyi
pytypegen/py.typed
pytypegen/pyty.py
pytypegen/pyty.pyi
pytypegen/contrib/__init__.py
pytypegen/contrib/__init__.pyi
pytypegen/contrib/contracts.py
pytypegen/contrib/contracts.pyi
pytypegen/contrib/jwt_auth.py
pytypegen/contrib/jwt_auth.pyi
pytypegen/contrib/py.typed
pytypegen-1.0.4.dist-info/METADATA
pytypegen-1.0.4.dist-info/RECORD
pytypegen-1.0.4.dist-info/WHEEL
pytypegen-1.0.4.dist-info/top_level.txt
